axi_ar_channel.py
axi_aw_channel.py
axi_b_channel.py
axi_connectN.py
axi_parameter.py
axi_r_channel.py
axi_w_channel.py
verilog_axi4.py
verilog_axi4-0.12.dist-info/METADATA
verilog_axi4-0.12.dist-info/WHEEL
verilog_axi4-0.12.dist-info/top_level.txt
verilog_axi4-0.12.dist-info/RECORD
