Metadata-Version: 2.1
Name: verilog-axi4
Version: 0.12
Summary: A module for generating verilog axi4 code
Home-page: UNKNOWN
Author: likmi
Author-email: likmi@qq.com
License: MIT
Platform: UNKNOWN
